LICENSE.txt
MANIFEST.in
setup.py
nltkrest/__init__.py
nltkrest/server.py
nltkrest.egg-info/PKG-INFO
nltkrest.egg-info/SOURCES.txt
nltkrest.egg-info/dependency_links.txt
nltkrest.egg-info/entry_points.txt
nltkrest.egg-info/requires.txt
nltkrest.egg-info/top_level.txt
nltkrest.egg-info/zip-safe