Metadata-Version: 1.1
Name: nltkrest
Version: 0.12
Summary: NLTK as a REST service
Home-page: https://github.com/manalishah/NLTKRest
Author: Manali Shah
Author-email: manalids@usc.edu
License: 
